README.md
simsam/__init__.py
simsam/simsam.py
simsam-0.1.3.dist-info/LICENSE.md
simsam-0.1.3.dist-info/WHEEL
simsam-0.1.3.dist-info/METADATA
simsam-0.1.3.dist-info/RECORD
