Metadata-Version: 2.1
Name: simsam
Version: 0.1.3
Summary: Simplex sampling algorithm
Home-page: https://github.com/Pseudomanifold/Simsam
License: BSD-3-Clause
Author: Bastian Rieck
Author-email: bastian@rieck.me
Requires-Python: >=3.9,<4.0
Classifier: License :: OSI Approved :: BSD License
Classifier: Programming Language :: Python :: 3
Classifier: Programming Language :: Python :: 3.9
Requires-Dist: numpy (>=1.19.4,<2.0.0)
Project-URL: Repository, https://github.com/Pseudomanifold/Simsam
